lc_flask_routes/__init__.py
lc_flask_routes/registry.py
lc_flask_routes/route.py
lc_flask_routes-0.1.0.dist-info/LICENSE
lc_flask_routes-0.1.0.dist-info/METADATA
lc_flask_routes-0.1.0.dist-info/WHEEL
lc_flask_routes-0.1.0.dist-info/top_level.txt
lc_flask_routes-0.1.0.dist-info/RECORD
