Metadata-Version: 2.1
Name: lc-flask-routes
Version: 0.1.0
Summary: UNKNOWN
Home-page: https://github.com/libcommon/flask-routes-py
Author: libcommon
Author-email: libcommon@protonmail.com
License: UNKNOWN
Project-URL: Issue Tracker, https://github.com/libcommon/flask-routes-py/issues
Project-URL: Releases, https://github.com/libcommon/flask-routes-py/releases
Platform: UNKNOWN
Classifier: Intended Audience :: Developers
Classifier: Programming Language :: Python :: 3
Classifier: License :: OSI Approved :: MIT License
Classifier: Operating System :: OS Independent
Requires-Python: >=3.6
Requires-Dist: Flask
Provides-Extra: all
Requires-Dist: lc-flask-reqparser ; extra == 'all'
Requires-Dist: lc-registry ; extra == 'all'
Provides-Extra: registry
Requires-Dist: lc-registry ; extra == 'registry'
Provides-Extra: reqparser
Requires-Dist: lc-flask-reqparser ; extra == 'reqparser'
